readme_generator/__init__.py
readme_generator/generate.py
readme_generator/template.py
readme_generator-0.0.2.dist-info/LICENSE
readme_generator-0.0.2.dist-info/METADATA
readme_generator-0.0.2.dist-info/WHEEL
readme_generator-0.0.2.dist-info/top_level.txt
readme_generator-0.0.2.dist-info/RECORD
