Metadata-Version: 2.1
Name: readme-generator
Version: 0.0.2
Summary: Very simple readme generator
Home-page: https://github.com/piotrostr/readme_generator
Author: Piotr Ostrowski
Author-email: piotr.ostrowski@aol.com
License: UNKNOWN
Project-URL: Bug Tracker, https://github.com/pypa/sampleproject/issues
Platform: UNKNOWN
Classifier: Programming Language :: Python :: 3
Classifier: License :: OSI Approved :: MIT License
Classifier: Operating System :: OS Independent
Requires-Python: >=3.6
License-File: LICENSE
